tests/__init__.py
tests/test.py
whale_api-0.0.1.dist-info/DESCRIPTION.rst
whale_api-0.0.1.dist-info/METADATA
whale_api-0.0.1.dist-info/RECORD
whale_api-0.0.1.dist-info/WHEEL
whale_api-0.0.1.dist-info/metadata.json
whale_api-0.0.1.dist-info/top_level.txt
whaleapi/__init__.py
whaleapi/api/__init__.py
whaleapi/api/base.py
whaleapi/api/events.py
whaleapi/api/exceptions.py
whaleapi/api/metrics.py
whaleapi/utils/__init__.py
whaleapi/utils/config.py
whaleapi/utils/converter.py
whaleapi/utils/hostname.py
