Metadata-Version: 2.0
Name: whale-api
Version: 0.0.1
Summary: Whale Monitoring API
Home-page: git@github.com:WhaleMonitoring/whale-api.git
Author: Whale Monitoring
Author-email: eirik@sylliaas.no
License: MIT
Keywords: Monitoring,Linux,Whale
Platform: UNKNOWN
Classifier: Intended Audience :: Developers
Classifier: License :: OSI Approved :: MIT License
Classifier: Natural Language :: English
Classifier: Programming Language :: Python :: 2
Classifier: Programming Language :: Python :: 2.7
Classifier: Programming Language :: Python :: 3
Classifier: Programming Language :: Python :: 3.4
Classifier: Programming Language :: Python :: 3.5
Requires-Dist: requests (==2.8.1)
Requires-Dist: six
